LICENSE
MANIFEST.in
README.rst
requirements.txt
setup.cfg
setup.py
django_script_pattern.egg-info/PKG-INFO
django_script_pattern.egg-info/SOURCES.txt
django_script_pattern.egg-info/dependency_links.txt
django_script_pattern.egg-info/requires.txt
django_script_pattern.egg-info/top_level.txt
script_pattern/__init__.py
script_pattern/admin.py
script_pattern/apps.py
script_pattern/const.py
script_pattern/forms.py
script_pattern/models.py
script_pattern/tests.py
script_pattern/views.py
script_pattern/locale/ar/LC_MESSAGES/django.po
script_pattern/locale/be/LC_MESSAGES/django.po
script_pattern/locale/bg/LC_MESSAGES/django.po
script_pattern/locale/bn/LC_MESSAGES/django.po
script_pattern/locale/cs/LC_MESSAGES/django.po
script_pattern/locale/da/LC_MESSAGES/django.po
script_pattern/locale/de/LC_MESSAGES/django.po
script_pattern/locale/en/LC_MESSAGES/django.po
script_pattern/locale/es/LC_MESSAGES/django.po
script_pattern/locale/fr/LC_MESSAGES/django.po
script_pattern/locale/it/LC_MESSAGES/django.po
script_pattern/locale/ja/LC_MESSAGES/django.po
script_pattern/locale/pl/LC_MESSAGES/django.po
script_pattern/locale/pt/LC_MESSAGES/django.po
script_pattern/locale/ru/LC_MESSAGES/django.po
script_pattern/locale/sv/LC_MESSAGES/django.po
script_pattern/locale/uk/LC_MESSAGES/django.po
script_pattern/locale/zh/LC_MESSAGES/django.po
script_pattern/migrations/0001_initial.py
script_pattern/migrations/0002_auto_20190514_1512.py
script_pattern/migrations/__init__.py
script_pattern/templatetags/__init__.py
script_pattern/templatetags/script_pattern_tags.py