Metadata-Version: 2.1
Name: django-script-pattern
Version: 0.3.3
Summary: Django script pattern app
Home-page: https://gitlab.com/kastielspb/django-script-pattern
Author: Maxim Shaitanov
Author-email: maximshaitanov@gmail.com
License: MIT
Platform: UNKNOWN
Classifier: Environment :: Web Environment
Classifier: Operating System :: OS Independent
Classifier: Framework :: Django
Classifier: Intended Audience :: Developers
Classifier: Programming Language :: Python :: 3.6
Classifier: Programming Language :: Python :: 3.7
